{
  "_object": "/api/response",
  "self": "https://api.flexport.com/shipment_legs/4064594",
  "version": 2,
  "data": {
    "_object": "/shipment_leg",
    "id": 4064594,
    "shipment": {
      "_object": "/api/refs/object",
      "ref_type": "/shipment",
      "link": "https://api.flexport.com/shipments/493053",
      "id": 493053
    },
    "estimated_arrival_date": null,
    "actual_arrival_date": null,
    "estimated_departure_date": null,
    "actual_departure_date": null,
    "cargo_ready_date": null,
    "additional_dates": {},
    "origin": {
      "_object": "/shipment_node",
      "tags": [
        "port_of_unloading",
        "customs_entry",
        "fmc_port_of_unloading"
      ],
      "place": {
        "_object": "/place",
        "name": "Los Angeles, CA",
        "address": {
          "_object": "/address",
          "street_address": null,
          "street_address2": null,
          "city": "Los Angeles",
          "state": "CA",
          "country": "United States",
          "country_code": "US",
          "zip": null,
          "unlocode": "USLAX",
          "timezone": "America/Los_Angeles",
          "ref": "id-41538"
        },
        "details": [
          {
            "_object": "/ocean/railport",
            "port_code": "2704"
          },
          {
            "_object": "/trucking/port",
            "port_code": "2704"
          },
          {
            "_object": "/ocean/port",
            "port_code": "2704"
          }
        ]
      },
      "terminal": null
    },
    "destination": {
      "_object": "/shipment_node",
      "tags": [
        "destination_address",
        "deconsolidation"
      ],
      "place": {
        "_object": "/place",
        "name": "Flexport Los Angeles Warehouse (OLD LOCATION)",
        "address": {
          "_object": "/address",
          "street_address": "6201 Knott Avenue",
          "street_address2": null,
          "city": "Buena Park",
          "state": "CA",
          "country": "United States",
          "country_code": "US",
          "zip": "90620",
          "unlocode": null,
          "timezone": "America/Los_Angeles",
          "ref": "id-227012"
        },
        "details": []
      },
      "terminal": null
    },
    "transportation_mode": "truck",
    "carrier_name": null,
    "ocean_leg": null,
    "air_leg": null,
    "trucking_leg": {
      "_object": "/trucking/shipment_leg",
      "tracking_number": null,
      "service_type": "drayage",
      "pieces": null,
      "container_legs": {
        "_object": "/api/refs/collection",
        "ref_type": "/ocean/shipment_container_leg",
        "link": "https://api.flexport.com/ocean/shipment_container_legs?f.leg.id=4064594"
      }
    },
    "rail_leg": null
  },
  "error": null
}